{
    "Q.N.AR.W1.S1.S1.LE.N.FA._T.F._Z.USD._T._X.N": "B90",
    "Q.N.AR.W1.S1.S1.LE.A.FA._T.F._Z.USD._T._X.N": "A",
    "Q.N.AR.W1.S1.S1.LE.A.FA.D.F._Z.USD._T._X.N": "A.1",
    "Q.N.AR.W1.S1.S1.LE.A.FA.D.F5._Z.USD._T._X.N": "A.1.1",
    "Q.N.AR.W1.S1.S1.LE.A.FA.D.FL._Z.USD._T._X.N": "A.1.2",
    "Q.N.AR.W1.S1.S1.LE.A.FA.P.F._Z.USD._T.M.N": "A.2",
    "Q.N.AR.W1.S1.S1.LE.A.FA.P.F5._Z.USD._T.M.N": "A.2.1",
    "Q.N.AR.W1.S122.S1.LE.A.FA.P.F5._Z.USD._T.M.N": "A.2.1.2",
    "Q.N.AR.W1.S1Z.S1.LE.A.FA.P.F5._Z.USD._T.M.N": "A.2.1.4",
    "Q.N.AR.W1.S1.S1.LE.A.FA.P.F3.T.USD._T.M.N": "A.2.2",
    "Q.N.AR.W1.S122.S1.LE.A.FA.P.F3.T.USD._T.M.N": "A.2.2.2",
    "Q.N.AR.W1.S13.S1.LE.A.FA.P.F3.T.USD._T.M.N": "A.2.2.3",
    "Q.N.AR.W1.S1Z.S1.LE.A.FA.P.F3.T.USD._T.M.N": "A.2.2.4",
    "Q.N.AR.W1.S1.S1.LE.A.FA.F.F7.T.USD._T.T.N": "A.3",
    "Q.N.AR.W1.S1.S1.LE.A.FA.O.F._Z.USD._T._X.N": "A.4",
    "Q.N.AR.W1.S1.S1.LE.A.FA.O.F519._Z.USD._T.M.N": "A.4.1",
    "Q.N.AR.W1.S1.S1.LE.A.FA.O.F2.T.USD._T.N.N": "A.4.2",
    "Q.N.AR.W1.S121.S1.LE.A.FA.O.F2.T.USD._T.N.N": "A.4.2.1",
    "Q.N.AR.W1.S122.S1.LE.A.FA.O.F2.T.USD._T.N.N": "A.4.2.2",
    "Q.N.AR.W1.S13.S1.LE.A.FA.O.F2.T.USD._T.N.N": "A.4.2.3",
    "Q.N.AR.W1.S1Z.S1.LE.A.FA.O.F2.T.USD._T.N.N": "A.4.2.4",
    "Q.N.AR.W1.S1.S1.LE.A.FA.O.F4.T.USD._T.N.N": "A.4.3",
    "Q.N.AR.W1.S121.S1.LE.A.FA.O.F4.T.USD._T.N.N": "A.4.3.1",
    "Q.N.AR.W1.S122.S1.LE.A.FA.O.F4.T.USD._T.N.N": "A.4.3.2",
    "Q.N.AR.W1.S13.S1.LE.A.FA.O.F4.T.USD._T.N.N": "A.4.3.3",
    "Q.N.AR.W1.S1Z.S1.LE.A.FA.O.F4.T.USD._T.N.N": "A.4.3.4",
    "Q.N.AR.W1.S1.S1.LE.A.FA.O.F6._Z.USD._T._X.N": "A.4.4",
    "Q.N.AR.W1.S1.S1.LE.A.FA.O.F81.T.USD._T._X.N": "A.4.5",
    "Q.N.AR.W1.S121.S1.LE.A.FA.O.F81.T.USD._T._X.N": "A.4.5.1",
    "Q.N.AR.W1.S122.S1.LE.A.FA.O.F81.T.USD._T._X.N": "A.4.5.2",
    "Q.N.AR.W1.S13.S1.LE.A.FA.O.F81.T.USD._T._X.N": "A.4.5.3",
    "Q.N.AR.W1.S1Z.S1.LE.A.FA.O.F81.T.USD._T._X.N": "A.4.5.4",
    "Q.N.AR.W1.S1.S1.LE.A.FA.O.F89.T.USD._T._X.N": "A.4.6",
    "Q.N.AR.W1.S121.S1.LE.A.FA.O.F89.T.USD._T._X.N": "A.4.6.1",
    "Q.N.AR.W1.S122.S1.LE.A.FA.O.F89.T.USD._T._X.N": "A.4.6.2",
    "Q.N.AR.W1.S13.S1.LE.A.FA.O.F89.T.USD._T._X.N": "A.4.6.3",
    "Q.N.AR.W1.S1Z.S1.LE.A.FA.O.F89.T.USD._T._X.N": "A.4.6.4",
    "Q.N.AR.W1.S121.S1.LE.A.FA.R.F._Z.USD.X1._X.N": "A.5",
    "Q.N.AR.W1.S121.S1.LE.A.FA.R.F11._Z.USD.XAU.M.N": "A.5.1",
    "Q.N.AR.W1.S121.S1N.LE.A.FA.R.F12.T.USD.XDR.M.N": "A.5.2",
    "Q.N.AR.1C.S121.S121.LE.A.FA.R.FK._Z.USD.XDR.M.N": "A.5.3",
    "Q.N.AR.W1.S121.S1.LE.A.FA.R.FR2._Z.USD.X1._X.N": "A.5.4",
    "Q.N.AR.W1.S121.S1.LE.A.FA.R.F2.T.USD.X1.N.N": "A.5.4.1",
    "Q.N.AR.W1.S121.S1.LE.A.FA.R.FR1._Z.USD.X1.M.N": "A.5.4.2",
    "Q.N.AR.W1.S121.S1.LE.A.FA.R.FR41._Z.USD.X1._X.N": "A.5.4.4",
    "Q.N.AR.W1.S1.S1.LE.L.FA._T.F._Z.USD._T._X.N": "P",
    "Q.N.AR.W1.S1.S1.LE.L.FA.D.F._Z.USD._T._X.N": "P.1",
    "Q.N.AR.W1.S1.S1.LE.L.FA.D.F5._Z.USD._T._X.N": "P.1.1",
    "Q.N.AR.W1.S1.S1.LE.L.FA.D.FL._Z.USD._T._X.N": "P.1.2",
    "Q.N.AR.W1.S1.S1.LE.L.FA.P.F._Z.USD._T.M.N": "P.2",
    "Q.N.AR.W1.S1.S1.LE.L.FA.P.F5._Z.USD._T.M.N": "P.2.1",
    "Q.N.AR.W1.S122.S1.LE.L.FA.P.F5._Z.USD._T.M.N": "P.2.1.2",
    "Q.N.AR.W1.S1Z.S1.LE.L.FA.P.F5._Z.USD._T.M.N": "P.2.1.4",
    "Q.N.AR.W1.S1.S1.LE.L.FA.P.F3.T.USD._T.M.N": "P.2.2",
    "Q.N.AR.W1.S121.S1.LE.L.FA.P.F3.T.USD._T.M.N": "P.2.2.1",
    "Q.N.AR.W1.S122.S1.LE.L.FA.P.F3.T.USD._T.M.N": "P.2.2.2",
    "Q.N.AR.W1.S13.S1.LE.L.FA.P.F3.T.USD._T.M.N": "P.2.2.3",
    "Q.N.AR.W1.S1Z.S1.LE.L.FA.P.F3.T.USD._T.M.N": "P.2.2.4",
    "Q.N.AR.W1.S1.S1.LE.L.FA.F.F7.T.USD._T.T.N": "P.3",
    "Q.N.AR.W1.S122.S1.LE.L.FA.F.F7.T.USD._T.T.N": "P.3.2",
    "Q.N.AR.W1.S13.S1.LE.L.FA.F.F7.T.USD._T.T.N": "P.3.3",
    "Q.N.AR.W1.S1Z.S1.LE.L.FA.F.F7.T.USD._T.T.N": "P.3.4",
    "Q.N.AR.W1.S1.S1.LE.L.FA.O.F._Z.USD._T._X.N": "P.4",
    "Q.N.AR.W1.S1.S1.LE.L.FA.O.F2.T.USD._T.N.N": "P.4.2",
    "Q.N.AR.W1.S121.S1.LE.L.FA.O.F2.T.USD._T.N.N": "P.4.2.1",
    "Q.N.AR.W1.S122.S1.LE.L.FA.O.F2.T.USD._T.N.N": "P.4.2.2",
    "Q.N.AR.W1.S13.S1.LE.L.FA.O.F2.T.USD._T.N.N": "P.4.2.3",
    "Q.N.AR.W1.S1Z.S1.LE.L.FA.O.F2.T.USD._T.N.N": "P.4.2.4",
    "Q.N.AR.W1.S1.S1.LE.L.FA.O.F4.T.USD._T.N.N": "P.4.3",
    "Q.N.AR.W1.S121.S1.LE.L.FA.O.F4.T.USD._T.N.N": "P.4.3.1",
    "Q.N.AR.W1.S122.S1.LE.L.FA.O.F4.T.USD._T.N.N": "P.4.3.2",
    "Q.N.AR.W1.S13.S1.LE.L.FA.O.F4.T.USD._T.N.N": "P.4.3.3",
    "Q.N.AR.W1.S1Z.S1.LE.L.FA.O.F4.T.USD._T.N.N": "P.4.3.4",
    "Q.N.AR.W1.S1.S1.LE.L.FA.O.F6._Z.USD._T._X.N": "P.4.4",
    "Q.N.AR.W1.S1.S1.LE.L.FA.O.F81.T.USD._T._X.N": "P.4.5",
    "Q.N.AR.W1.S121.S1.LE.L.FA.O.F81.T.USD._T._X.N": "P.4.5.1",
    "Q.N.AR.W1.S122.S1.LE.L.FA.O.F81.T.USD._T._X.N": "P.4.5.2",
    "Q.N.AR.W1.S13.S1.LE.L.FA.O.F81.T.USD._T._X.N": "P.4.5.3",
    "Q.N.AR.W1.S1Z.S1.LE.L.FA.O.F81.T.USD._T._X.N": "P.4.5.4",
    "Q.N.AR.W1.S1.S1.LE.L.FA.O.F89.T.USD._T._X.N": "P.4.6",
    "Q.N.AR.W1.S121.S1.LE.L.FA.O.F89.T.USD._T._X.N": "P.4.6.1",
    "Q.N.AR.W1.S122.S1.LE.L.FA.O.F89.T.USD._T._X.N": "P.4.6.2",
    "Q.N.AR.W1.S13.S1.LE.L.FA.O.F89.T.USD._T._X.N": "P.4.6.3",
    "Q.N.AR.W1.S1Z.S1.LE.L.FA.O.F89.T.USD._T._X.N": "P.4.6.4",
    "Q.N.AR.W1.S1.S1N.LE.L.FA.O.F12.T.USD._T._X.N": "P.4.7"
}